domainmodelexaminer/__init__.py
domainmodelexaminer/api.py
domainmodelexaminer/arbitrary_miner.py
domainmodelexaminer/dmx.py
domainmodelexaminer/docker_miner.py
domainmodelexaminer/getcomments.py
domainmodelexaminer/julia_miner.py
domainmodelexaminer/language.py
domainmodelexaminer/python_miner.py
domainmodelexaminer/r_miner.py
domainmodelexaminer/repo_miner.py
domainmodelexaminer/utilities.py
domainmodelexaminer/data_files/model-type-libraries.json
domainmodelexaminer/data_files/parameters.json
domainmodelexaminer-0.1.1.dist-info/LICENSE
domainmodelexaminer-0.1.1.dist-info/METADATA
domainmodelexaminer-0.1.1.dist-info/WHEEL
domainmodelexaminer-0.1.1.dist-info/top_level.txt
domainmodelexaminer-0.1.1.dist-info/RECORD
