Metadata-Version: 2.1
Name: domainmodelexaminer
Version: 0.1.1
Summary: A library to perform machine reading over a model codebase in order to automatically extract key metadata.
Home-page: https://github.com/dojo-modeling/domain-model-examiner
Author: Robnet Kerns
Author-email: robnet@jataware.com
License: MIT license
Keywords: domainmodelexaminer
Platform: UNKNOWN
Classifier: Development Status :: 2 - Pre-Alpha
Classifier: Intended Audience :: Developers
Classifier: License :: OSI Approved :: MIT License
Classifier: Natural Language :: English
Classifier: Programming Language :: Python :: 3
Classifier: Programming Language :: Python :: 3.8
Requires-Python: >=3.8
License-File: LICENSE
Requires-Dist: tldextract (>=3.1.0)
Requires-Dist: PyYAML (>=5.4.1)
Requires-Dist: GitPython (>=3.1.14)
Requires-Dist: fastapi[all]
